{"cameraMode":{"drawMode":0,"name":"Shaded","section":"Shading Mode"},"sceneLighting":false,"audioPlay":false,"sceneViewState":{"m_AlwaysRefresh":false,"showFog":true,"showSkybox":false,"showFlares":true,"showImageEffects":true,"showParticleSystems":true,"showVisualEffectGraphs":true,"m_FxEnabled":true},"in2DMode":false,"pivot":{"x":362.5,"y":209.0,"z":0.0},"rotation":{"x":0.03655177354812622,"y":0.49166539311408999,"z":-0.020661955699324609,"w":0.8697712421417236},"size":49.497474670410159,"orthographic":false}